{
  "project_info": {
    "project_number": "583486626331",
    "project_id": "cofflyze",
    "storage_bucket": "cofflyze.firebasestorage.app"
  },
  "client": [
    {
      "client_info": {
        "mobilesdk_app_id": "1:583486626331:android:76fc5a66d8c0a1eb7976be",
        "android_client_info": {
          "package_name": "com.capstone.cofflyze"
        }
      },
      "oauth_client": [],
      "api_key": [
        {
          "current_key": "AIzaSyC6poAlIG8Hi-ZkZLgRAQNBDrnG1x1AHBU"
        }
      ],
      "services": {
        "appinvite_service": {
          "other_platform_oauth_client": []
        }
      }
    }
  ],
  "configuration_version": "1"
}